sqlbench/__init__.py
sqlbench/__main__.py
sqlbench/adapters.py
sqlbench/app.py
sqlbench/database.py
sqlbench/launcher.py
sqlbench/version.py
sqlbench/dialogs/__init__.py
sqlbench/dialogs/connection_dialog.py
sqlbench/dialogs/regex_builder_dialog.py
sqlbench/resources/db_ibmi.png
sqlbench/resources/db_mysql.png
sqlbench/resources/db_postgresql.png
sqlbench/resources/db_unknown.png
sqlbench/resources/sqlbench.png
sqlbench/tabs/__init__.py
sqlbench/tabs/spool_tab.py
sqlbench/tabs/sql_tab.py
sqlbench-0.1.29.dist-info/METADATA
sqlbench-0.1.29.dist-info/WHEEL
sqlbench-0.1.29.dist-info/entry_points.txt
sqlbench-0.1.29.dist-info/RECORD
